torch
torchgen
