Metadata-Version: 2.1
Name: torch_cpp
Version: 0.1.0
Summary: Tensors and Dynamic neural networks in Python with strong GPU acceleration
Home-page: https://pytorch.org/
Download-URL: https://github.com/pytorch/pytorch/tags
Author: PyTorch Team
Author-email: packages@pytorch.org
License: BSD-3
Keywords: pytorch,machine learning
Classifier: Development Status :: 5 - Production/Stable
Classifier: Intended Audience :: Developers
Classifier: Intended Audience :: Education
Classifier: Intended Audience :: Science/Research
Classifier: License :: OSI Approved :: BSD License
Classifier: Topic :: Scientific/Engineering
Classifier: Topic :: Scientific/Engineering :: Mathematics
Classifier: Topic :: Scientific/Engineering :: Artificial Intelligence
Classifier: Topic :: Software Development
Classifier: Topic :: Software Development :: Libraries
Classifier: Topic :: Software Development :: Libraries :: Python Modules
Classifier: Programming Language :: C++
Classifier: Programming Language :: Python :: 3
Classifier: Programming Language :: Python :: 3.8
Classifier: Programming Language :: Python :: 3.9
Classifier: Programming Language :: Python :: 3.10
Classifier: Programming Language :: Python :: 3.11
Classifier: Programming Language :: Python :: 3.12
Requires-Python: >=3.8.0
License-File: LICENSE
License-File: NOTICE
Requires-Dist: filelock
Requires-Dist: typing-extensions >=4.8.0
Requires-Dist: sympy
Requires-Dist: networkx
Requires-Dist: jinja2
Requires-Dist: fsspec
Provides-Extra: opt-einsum
Requires-Dist: opt-einsum >=3.3 ; extra == 'opt-einsum'
Provides-Extra: optree
Requires-Dist: optree >=0.11.0 ; extra == 'optree'
